envChecker/__init__.py
envChecker/check.py
envChecker/envCheck.py
envChecker-1.0.0.dist-info/LICENSE
envChecker-1.0.0.dist-info/METADATA
envChecker-1.0.0.dist-info/WHEEL
envChecker-1.0.0.dist-info/top_level.txt
envChecker-1.0.0.dist-info/RECORD
